ethiack_job_manager/__init__.py
ethiack_job_manager/cli.py
ethiack_job_manager/manager.py
ethiack_job_manager/types.py
ethiack_job_manager/utils.py
ethiack_job_manager-1.1.3.dist-info/licenses/LICENSE
ethiack_job_manager-1.1.3.dist-info/METADATA
ethiack_job_manager-1.1.3.dist-info/WHEEL
ethiack_job_manager-1.1.3.dist-info/entry_points.txt
ethiack_job_manager-1.1.3.dist-info/top_level.txt
ethiack_job_manager-1.1.3.dist-info/RECORD
