Metadata-Version: 2.4
Name: ethiack-job-manager
Version: 1.1.3
Summary: Python package for managing jobs using Ethiack's Public API
Author-email: Ethiack <hello@ethiack.com>
License:     MIT License
Project-URL: Homepage, https://ethiack.com
Project-URL: Repository, https://github.com/ethiack/job-manager.git
Project-URL: Issues, https://github.com/ethiack/job-manager/issues
Classifier: Development Status :: 5 - Production/Stable
Classifier: Intended Audience :: Developers
Classifier: License :: OSI Approved :: MIT License
Classifier: Programming Language :: Python :: 3 :: Only
Classifier: Programming Language :: Python :: 3.8
Classifier: Programming Language :: Python :: 3.9
Classifier: Programming Language :: Python :: 3.10
Classifier: Programming Language :: Python :: 3.11
Classifier: Programming Language :: Python :: 3.12
Requires-Python: >=3.8
License-File: LICENSE
Requires-Dist: click>=8
Requires-Dist: python-dotenv
Requires-Dist: pydantic>=2
Requires-Dist: requests
Requires-Dist: rich_click
Requires-Dist: tenacity
Provides-Extra: test
Requires-Dist: pytest; extra == "test"
Requires-Dist: pytest-cov; extra == "test"
Requires-Dist: mypy; extra == "test"
Provides-Extra: dev
Requires-Dist: ethiack-job-manager[test]; extra == "dev"
Provides-Extra: all
Requires-Dist: ethiack-job-manager[test]; extra == "all"
Requires-Dist: ethiack-job-manager[dev]; extra == "all"
Dynamic: license-file
